examples/01_basic_usage.py
examples/02_block_bridge.py
examples/03_player_monitor.py
examples/04_tower_builder.py
examples/05_teleport_circle.py
examples/06_server_monitor.py
examples/07_entity_spawner.py
examples/08_scoreboard_manager.py
examples/09_world_controller.py
examples/10_potion_effects.py
examples/11_inventory_manager.py
examples/12_particle_circle.py
examples/13_event_basic.py
examples/14_event_chat_bot.py
examples/15_event_advanced.py
examples/16_combat_stats.py
mcwebapi/__init__.py
mcwebapi/api.py
mcwebapi/py.typed
mcwebapi/core/__init__.py
mcwebapi/core/client.py
mcwebapi/core/connection.py
mcwebapi/events/__init__.py
mcwebapi/events/decorators.py
mcwebapi/events/manager.py
mcwebapi/events/types.py
mcwebapi/objects/__init__.py
mcwebapi/objects/base.py
mcwebapi/objects/block.py
mcwebapi/objects/command.py
mcwebapi/objects/entity.py
mcwebapi/objects/level.py
mcwebapi/objects/player.py
mcwebapi/objects/scoreboard.py
mcwebapi/objects/server.py
mcwebapi/types/__init__.py
mcwebapi/types/responses.py
mcwebapi-0.4.0.dist-info/licenses/LICENSE
mcwebapi-0.4.0.dist-info/METADATA
mcwebapi-0.4.0.dist-info/WHEEL
mcwebapi-0.4.0.dist-info/top_level.txt
mcwebapi-0.4.0.dist-info/RECORD
