Metadata-Version: 2.4
Name: mcwebapi
Version: 0.4.0
Summary: An async Python client for interacting with Minecraft servers via WebSocket API
Author: addavriance
License: MIT
Project-URL: Homepage, https://github.com/addavriance/mcwebapi
Project-URL: Bug Tracker, https://github.com/addavriance/mcwebapi/issues
Keywords: minecraft,api,websocket,client,async,asyncio
Classifier: Development Status :: 3 - Alpha
Classifier: Intended Audience :: Developers
Classifier: License :: OSI Approved :: MIT License
Classifier: Operating System :: OS Independent
Classifier: Programming Language :: Python :: 3
Classifier: Programming Language :: Python :: 3.8
Classifier: Programming Language :: Python :: 3.9
Classifier: Programming Language :: Python :: 3.10
Classifier: Programming Language :: Python :: 3.11
Classifier: Programming Language :: Python :: 3.12
Classifier: Framework :: AsyncIO
Requires-Python: >=3.8
License-File: LICENSE
Requires-Dist: websockets>=12.0
Dynamic: license-file
